{
  "id": "most-popular-tv-characters",
  "title": "Most Popular TV Characters",
  "items": [
    {
      "rank": 1,
      "name": "Homer Simpson"
    },
    {
      "rank": 2,
      "name": "Bart Simpson"
    },
    {
      "rank": 3,
      "name": "Walter White"
    },
    {
      "rank": 4,
      "name": "Jesse Pinkman"
    },
    {
      "rank": 5,
      "name": "Michael Scott"
    },
    {
      "rank": 6,
      "name": "Dwight Schrute"
    },
    {
      "rank": 7,
      "name": "Jim Halpert"
    },
    {
      "rank": 8,
      "name": "Pam Beesly"
    },
    {
      "rank": 9,
      "name": "Ross Geller"
    },
    {
      "rank": 10,
      "name": "Rachel Green"
    },
    {
      "rank": 11,
      "name": "Monica Geller"
    },
    {
      "rank": 12,
      "name": "Chandler Bing"
    },
    {
      "rank": 13,
      "name": "Joey Tribbiani"
    },
    {
      "rank": 14,
      "name": "Phoebe Buffay"
    },
    {
      "rank": 15,
      "name": "Eleven"
    },
    {
      "rank": 16,
      "name": "Tony Soprano"
    },
    {
      "rank": 17,
      "name": "Don Draper"
    },
    {
      "rank": 18,
      "name": "Sheldon Cooper"
    },
    {
      "rank": 19,
      "name": "Leonard Hofstadter"
    },
    {
      "rank": 20,
      "name": "Penny"
    },
    {
      "rank": 21,
      "name": "Tyrion Lannister"
    },
    {
      "rank": 22,
      "name": "Jon Snow"
    },
    {
      "rank": 23,
      "name": "Daenerys Targaryen"
    },
    {
      "rank": 24,
      "name": "Arya Stark"
    },
    {
      "rank": 25,
      "name": "Cersei Lannister"
    },
    {
      "rank": 26,
      "name": "Sherlock Holmes"
    },
    {
      "rank": 27,
      "name": "Dr. John Watson"
    },
    {
      "rank": 28,
      "name": "House"
    },
    {
      "rank": 29,
      "name": "Dr. Gregory House"
    },
    {
      "rank": 30,
      "name": "Dr. Wilson"
    },
    {
      "rank": 31,
      "name": "Leslie Knope"
    },
    {
      "rank": 32,
      "name": "Ron Swanson"
    },
    {
      "rank": 33,
      "name": "April Ludgate"
    },
    {
      "rank": 34,
      "name": "Andy Davenport"
    },
    {
      "rank": 35,
      "name": "Ben Wyatt"
    },
    {
      "rank": 36,
      "name": "Jerry Seinfeld"
    },
    {
      "rank": 37,
      "name": "George Costanza"
    },
    {
      "rank": 38,
      "name": "Elaine Benes"
    },
    {
      "rank": 39,
      "name": "Cosmo Kramer"
    },
    {
      "rank": 40,
      "name": "Lucy Ricardo"
    },
    {
      "rank": 41,
      "name": "Ricky Ricardo"
    },
    {
      "rank": 42,
      "name": "Ethel Mertz"
    },
    {
      "rank": 43,
      "name": "Fred Mertz"
    },
    {
      "rank": 44,
      "name": "Archie Bunker"
    },
    {
      "rank": 45,
      "name": "Edith Bunker"
    },
    {
      "rank": 46,
      "name": "Fonzie"
    },
    {
      "rank": 47,
      "name": "Richie Cunningham"
    },
    {
      "rank": 48,
      "name": "Mulder"
    },
    {
      "rank": 49,
      "name": "Scully"
    },
    {
      "rank": 50,
      "name": "Jack Bauer"
    },
    {
      "rank": 51,
      "name": "Carrie Bradshaw"
    },
    {
      "rank": 52,
      "name": "Samantha Jones"
    },
    {
      "rank": 53,
      "name": "Miranda Hobbes"
    },
    {
      "rank": 54,
      "name": "Charlotte York"
    },
    {
      "rank": 55,
      "name": "Mr. Big"
    },
    {
      "rank": 56,
      "name": "Olivia Benson"
    },
    {
      "rank": 57,
      "name": "Elliot Stabler"
    },
    {
      "rank": 58,
      "name": "Dexter Morgan"
    },
    {
      "rank": 59,
      "name": "Debra Morgan"
    },
    {
      "rank": 60,
      "name": "Hannibal Lecter"
    },
    {
      "rank": 61,
      "name": "Will Graham"
    },
    {
      "rank": 62,
      "name": "Rick Grimes"
    },
    {
      "rank": 63,
      "name": "Daryl Dixon"
    },
    {
      "rank": 64,
      "name": "Michonne"
    },
    {
      "rank": 65,
      "name": "Negan"
    },
    {
      "rank": 66,
      "name": "Homelander"
    },
    {
      "rank": 67,
      "name": "Billy Butcher"
    },
    {
      "rank": 68,
      "name": "Starlight"
    },
    {
      "rank": 69,
      "name": "Queen Maeve"
    },
    {
      "rank": 70,
      "name": "A-Train"
    },
    {
      "rank": 71,
      "name": "Ted Lasso"
    },
    {
      "rank": 72,
      "name": "Coach Beard"
    },
    {
      "rank": 73,
      "name": "Roy Kent"
    },
    {
      "rank": 74,
      "name": "Rebecca Welton"
    },
    {
      "rank": 75,
      "name": "Keeley Jones"
    },
    {
      "rank": 76,
      "name": "Geralt of Rivia"
    },
    {
      "rank": 77,
      "name": "Yennefer"
    },
    {
      "rank": 78,
      "name": "Ciri"
    },
    {
      "rank": 79,
      "name": "Jaskier"
    },
    {
      "rank": 80,
      "name": "Wednesday Addams"
    },
    {
      "rank": 81,
      "name": "Enid Sinclair"
    },
    {
      "rank": 82,
      "name": "Morticia Addams"
    },
    {
      "rank": 83,
      "name": "Gomez Addams"
    },
    {
      "rank": 84,
      "name": "Loki"
    },
    {
      "rank": 85,
      "name": "Mobius"
    },
    {
      "rank": 86,
      "name": "Saul Goodman"
    },
    {
      "rank": 87,
      "name": "Kim Wexler"
    },
    {
      "rank": 88,
      "name": "Gus Fring"
    },
    {
      "rank": 89,
      "name": "Mike Ehrmantraut"
    },
    {
      "rank": 90,
      "name": "Hank Schrader"
    },
    {
      "rank": 91,
      "name": "Carrie Mathison"
    },
    {
      "rank": 92,
      "name": "Brody"
    },
    {
      "rank": 93,
      "name": "Jack Pearson"
    },
    {
      "rank": 94,
      "name": "Rebecca Pearson"
    },
    {
      "rank": 95,
      "name": "Randall Pearson"
    },
    {
      "rank": 96,
      "name": "Kate Pearson"
    },
    {
      "rank": 97,
      "name": "Kevin Pearson"
    },
    {
      "rank": 98,
      "name": "Ted Mosby"
    },
    {
      "rank": 99,
      "name": "Barney Stinson"
    },
    {
      "rank": 100,
      "name": "Robin Scherbatsky"
    }
  ]
}
